ncconvert/__init__.py
ncconvert/__main__.py
ncconvert/_version.py
ncconvert/cli.py
ncconvert/csv.py
ncconvert/parquet.py
ncconvert/py.typed
ncconvert/utils.py
ncconvert-0.1.4.dist-info/LICENSE.md
ncconvert-0.1.4.dist-info/METADATA
ncconvert-0.1.4.dist-info/WHEEL
ncconvert-0.1.4.dist-info/entry_points.txt
ncconvert-0.1.4.dist-info/top_level.txt
ncconvert-0.1.4.dist-info/RECORD
