Metadata-Version: 2.1
Name: ncconvert
Version: 0.1.4
Summary: Convert netCDF to other formats.
Author-email: tsdat <tsdat@pnnl.gov>
License: Simplified BSD
Keywords: netCDF,cdf,nc
Classifier: Programming Language :: Python :: 3
Requires-Python: >=3.8
License-File: LICENSE.md
Requires-Dist: xarray[io]
Requires-Dist: pandas[parquet]
Provides-Extra: cli
Requires-Dist: typer >=0.9.0 ; extra == 'cli'
Requires-Dist: tqdm ; extra == 'cli'
Requires-Dist: rich ; extra == 'cli'
Provides-Extra: dev
Requires-Dist: pytest ; extra == 'dev'
Requires-Dist: coverage ; extra == 'dev'
Requires-Dist: build ; extra == 'dev'
Requires-Dist: black ; extra == 'dev'
Requires-Dist: ruff ; extra == 'dev'
Requires-Dist: isort ; extra == 'dev'
